SubCMedians/__init__.py
SubCMedians/data_generator.py
SubCMedians/evaluation.py
SubCMedians/genotype.py
SubCMedians/model.py
SubCMedians/phenotype.py
SubCMedians/subcmedians.py
SubCMedians/subcmedians_ensemble.py
SubCMedians/subcmedians_v1.py
SubCMedians/subcmedians_v2.py
SubCMedians/subcmedians_v3.py
SubCMedians/subcmedians_v4.py
SubCMedians-0.0.10.dist-info/LICENSE
SubCMedians-0.0.10.dist-info/METADATA
SubCMedians-0.0.10.dist-info/WHEEL
SubCMedians-0.0.10.dist-info/top_level.txt
SubCMedians-0.0.10.dist-info/RECORD
