Metadata-Version: 2.1
Name: SubCMedians
Version: 0.0.10
Summary: Weight-based Subspace Clustering
Home-page: 
Author: Sergio Peignier, Christophe Rigotti
Author-email: sergio.peignier@insa-lyon.fr
Classifier: Programming Language :: Python :: 3
Classifier: License :: OSI Approved :: GNU General Public License (GPL)
Classifier: Operating System :: OS Independent
License-File: LICENSE
Requires-Dist: pandas
Requires-Dist: numpy
Requires-Dist: scikit-learn
Requires-Dist: tqdm
Requires-Dist: scipy
